{
  "schema_version": 1,
  "client_slug": "",
  "active_provider": "widecast",
  "providers": {
    "widecast": {
      "type": "openapi",
      "discovery_url": "https://widecast.ai/openapi.yaml",
      "provider_home_url": "https://widecast.ai/",
      "auth_type": "bearer_api_key",
      "api_key_env": "",
      "api_key_local": "",
      "provider_identity_source": "per_client_openapi",
      "mcp_compatibility_status": "not_used",
      "pdna_setup_blocker": "",
      "account_verified_at": "",
      "account_identity": {
        "company_id": "",
        "email_masked": "",
        "name": "",
        "connected_platforms": []
      },
      "pdna": {
        "production": "not_configured",
        "distribution": "not_configured",
        "notification": "not_configured",
        "analytics": "not_configured"
      },
      "notification": {
        "enabled": false,
        "preferred_operation_id": "sendTelegramMessage",
        "delivery": "telegram_or_email_fallback"
      },
      "report_upload": {
        "enabled": false,
        "preferred_operation_id": "uploadAsset",
        "content_type": "text/html",
        "ttl_hours_note": "WideCast uploadAsset URLs may be short-lived. Use for report notifications, not permanent archives."
      }
    }
  }
}
